colabexts/__init__.py
colabexts/jcommon.ipynb
colabexts/jcommon.py
colabexts/log.py
colabexts/utils.py
colabexts/version.txt
colabexts-0.12300000000000003.dist-info/METADATA
colabexts-0.12300000000000003.dist-info/WHEEL
colabexts-0.12300000000000003.dist-info/top_level.txt
colabexts-0.12300000000000003.dist-info/RECORD
